npy_reader/__init__.py
npy_reader/npy_reader.py
npy_reader-1.1.2.dist-info/LICENSE
npy_reader-1.1.2.dist-info/METADATA
npy_reader-1.1.2.dist-info/WHEEL
npy_reader-1.1.2.dist-info/entry_points.txt
npy_reader-1.1.2.dist-info/top_level.txt
npy_reader-1.1.2.dist-info/RECORD
